pydanticai_genai_hub/__init__.py
pydanticai_genai_hub/anthropic.py
pydanticai_genai_hub/openai.py
pydanticai_genai_hub/providers.py
pydanticai_genai_hub-0.1.10.dist-info/licenses/LICENSE
pydanticai_genai_hub-0.1.10.dist-info/METADATA
pydanticai_genai_hub-0.1.10.dist-info/WHEEL
pydanticai_genai_hub-0.1.10.dist-info/top_level.txt
pydanticai_genai_hub-0.1.10.dist-info/RECORD
