Metadata-Version: 2.4
Name: pydanticai-genai-hub
Version: 0.1.10
Summary: SAP Generative AI Hub: Pydantic AI models for various LLM providers
Author-email: Gunter <albrechg@yahoo.com>
License: MIT
Project-URL: Homepage, https://github.com/skye0402/pydanticai-genaihub
Project-URL: Repository, https://github.com/skye0402/pydanticai-genaihub.git
Classifier: Development Status :: 3 - Alpha
Classifier: Intended Audience :: Developers
Classifier: License :: OSI Approved :: MIT License
Classifier: Operating System :: OS Independent
Classifier: Programming Language :: Python :: 3
Classifier: Programming Language :: Python :: 3.12
Requires-Python: >=3.12
License-File: LICENSE
Requires-Dist: pydantic>=2.11.1
Requires-Dist: pydantic-ai>=0.0.49
Requires-Dist: typing-extensions>=4.0.0
Requires-Dist: httpx>=0.24.0
Requires-Dist: generative-ai-hub-sdk>=3.8.0
Provides-Extra: anthropic
Requires-Dist: anthropic>=0.3.0; extra == "anthropic"
Provides-Extra: openai
Requires-Dist: openai>=1.0.0; extra == "openai"
Provides-Extra: all
Requires-Dist: anthropic>=0.3.0; extra == "all"
Requires-Dist: openai>=1.0.0; extra == "all"
Dynamic: license-file
